{
  "size": 11,
  "name": "map04",
  "spawn_points": [
    {
      "at_spg": [
        {
          "x": -3,
          "y": -7,
          "z": 10
        }
      ],
      "heavy_tank": [
        {
          "x": -5,
          "y": -5,
          "z": 10
        }
      ],
      "light_tank": [
        {
          "x": -6,
          "y": -4,
          "z": 10
        }
      ],
      "medium_tank": [
        {
          "x": -4,
          "y": -6,
          "z": 10
        }
      ],
      "spg": [
        {
          "x": -7,
          "y": -3,
          "z": 10
        }
      ]
    },
    {
      "at_spg": [
        {
          "x": -7,
          "y": 10,
          "z": -3
        }
      ],
      "heavy_tank": [
        {
          "x": -5,
          "y": 10,
          "z": -5
        }
      ],
      "light_tank": [
        {
          "x": -4,
          "y": 10,
          "z": -6
        }
      ],
      "medium_tank": [
        {
          "x": -6,
          "y": 10,
          "z": -4
        }
      ],
      "spg": [
        {
          "x": -3,
          "y": 10,
          "z": -7
        }
      ]
    },
    {
      "at_spg": [
        {
          "x": 10,
          "y": -3,
          "z": -7
        }
      ],
      "heavy_tank": [
        {
          "x": 10,
          "y": -5,
          "z": -5
        }
      ],
      "light_tank": [
        {
          "x": 10,
          "y": -6,
          "z": -4
        }
      ],
      "medium_tank": [
        {
          "x": 10,
          "y": -4,
          "z": -6
        }
      ],
      "spg": [
        {
          "x": 10,
          "y": -7,
          "z": -3
        }
      ]
    }
  ],
  "content": {
    "base": [
      {
        "x": -1,
        "y": 0,
        "z": 1
      },
      {
        "x": -1,
        "y": 1,
        "z": 0
      },
      {
        "x": 0,
        "y": -1,
        "z": 1
      },
      {
        "x": 0,
        "y": 0,
        "z": 0
      },
      {
        "x": 0,
        "y": 1,
        "z": -1
      },
      {
        "x": 1,
        "y": -1,
        "z": 0
      },
      {
        "x": 1,
        "y": 0,
        "z": -1
      }
    ],
    "obstacle": [
      {
        "x": -10,
        "y": 0,
        "z": 10
      },
      {
        "x": -10,
        "y": 10,
        "z": 0
      },
      {
        "x": -9,
        "y": 0,
        "z": 9
      },
      {
        "x": -9,
        "y": 9,
        "z": 0
      },
      {
        "x": -8,
        "y": 0,
        "z": 8
      },
      {
        "x": -8,
        "y": 8,
        "z": 0
      },
      {
        "x": -7,
        "y": 0,
        "z": 7
      },
      {
        "x": -7,
        "y": 7,
        "z": 0
      },
      {
        "x": -6,
        "y": 0,
        "z": 6
      },
      {
        "x": -6,
        "y": 6,
        "z": 0
      },
      {
        "x": -5,
        "y": 0,
        "z": 5
      },
      {
        "x": -5,
        "y": 5,
        "z": 0
      },
      {
        "x": -3,
        "y": 0,
        "z": 3
      },
      {
        "x": -3,
        "y": 3,
        "z": 0
      },
      {
        "x": -2,
        "y": 0,
        "z": 2
      },
      {
        "x": -2,
        "y": 2,
        "z": 0
      },
      {
        "x": 0,
        "y": -10,
        "z": 10
      },
      {
        "x": 0,
        "y": -9,
        "z": 9
      },
      {
        "x": 0,
        "y": -8,
        "z": 8
      },
      {
        "x": 0,
        "y": -7,
        "z": 7
      },
      {
        "x": 0,
        "y": -6,
        "z": 6
      },
      {
        "x": 0,
        "y": -5,
        "z": 5
      },
      {
        "x": 0,
        "y": -3,
        "z": 3
      },
      {
        "x": 0,
        "y": -2,
        "z": 2
      },
      {
        "x": 0,
        "y": 2,
        "z": -2
      },
      {
        "x": 0,
        "y": 3,
        "z": -3
      },
      {
        "x": 0,
        "y": 5,
        "z": -5
      },
      {
        "x": 0,
        "y": 6,
        "z": -6
      },
      {
        "x": 0,
        "y": 7,
        "z": -7
      },
      {
        "x": 0,
        "y": 8,
        "z": -8
      },
      {
        "x": 0,
        "y": 9,
        "z": -9
      },
      {
        "x": 0,
        "y": 10,
        "z": -10
      },
      {
        "x": 2,
        "y": -2,
        "z": 0
      },
      {
        "x": 2,
        "y": 0,
        "z": -2
      },
      {
        "x": 3,
        "y": -3,
        "z": 0
      },
      {
        "x": 3,
        "y": 0,
        "z": -3
      },
      {
        "x": 5,
        "y": -5,
        "z": 0
      },
      {
        "x": 5,
        "y": 0,
        "z": -5
      },
      {
        "x": 6,
        "y": -6,
        "z": 0
      },
      {
        "x": 6,
        "y": 0,
        "z": -6
      },
      {
        "x": 7,
        "y": -7,
        "z": 0
      },
      {
        "x": 7,
        "y": 0,
        "z": -7
      },
      {
        "x": 8,
        "y": -8,
        "z": 0
      },
      {
        "x": 8,
        "y": 0,
        "z": -8
      },
      {
        "x": 9,
        "y": -9,
        "z": 0
      },
      {
        "x": 9,
        "y": 0,
        "z": -9
      },
      {
        "x": 10,
        "y": -10,
        "z": 0
      },
      {
        "x": 10,
        "y": 0,
        "z": -10
      }
    ]
  }
}